flake8_scream/__init__.py
flake8_scream/rules/__init__.py
flake8_scream/rules/ast_unary_op.py
flake8_scream-0.1.0.dist-info/LICENSE
flake8_scream-0.1.0.dist-info/METADATA
flake8_scream-0.1.0.dist-info/WHEEL
flake8_scream-0.1.0.dist-info/entry_points.txt
flake8_scream-0.1.0.dist-info/top_level.txt
flake8_scream-0.1.0.dist-info/RECORD
