Metadata-Version: 2.1
Name: flake8-scream
Version: 0.1.0
Summary: flake8 plugin which checks for code that can be simplified
Home-page: https://github.com/MartinThoma/flake8-scream
Author: Martin Thoma
Author-email: info@martin-thoma.de
Maintainer: Martin Thoma
Maintainer-email: info@martin-thoma.de
License: MIT
Keywords: flake8
Platform: UNKNOWN
Classifier: Development Status :: 4 - Beta
Classifier: Environment :: Console
Classifier: Intended Audience :: Developers
Classifier: License :: OSI Approved :: MIT License
Classifier: Natural Language :: English
Classifier: Operating System :: OS Independent
Classifier: Programming Language :: Python :: 3
Classifier: Programming Language :: Python :: 3 :: Only
Classifier: Programming Language :: Python :: 3.7
Classifier: Programming Language :: Python :: 3.8
Classifier: Programming Language :: Python :: 3.9
Classifier: Programming Language :: Python :: 3.10
Classifier: Topic :: Software Development
Classifier: Framework :: Flake8
Requires-Python: >=3.6.1
License-File: LICENSE
Requires-Dist: flake8 (>=3.7)
Requires-Dist: flake8-simplify (>=0.18.2)
Requires-Dist: astor (>=0.1)
Requires-Dist: importlib-metadata (>=0.9) ; python_version < "3.8"
